pyseqfile/__init__.py
pyseqfile/cseq_file.pxd
pyseqfile/main.py
pyseqfile/seqfile.c
pyseqfile/seqfile.cpython-35m-darwin.so
pyseqfile/seqfile.pyx
pyseqfile/seqfile.so
pyseqfile-0.0.2.dist-info/WHEEL
pyseqfile-0.0.2.dist-info/METADATA
pyseqfile-0.0.2.dist-info/RECORD
