Metadata-Version: 1.2
Name: pyseqfile
Version: 0.0.2
Summary: Fast parsing of multiple sequence file formats using seq_file
Home-page: https://github.com/Phelimb/pyseqfile
License: UNKNOWN
Author: Phelim Bradley
Author-email: wave@phel.im
Classifier: License :: OSI Approved :: MIT License
